sticker/__init__.py
sticker/openapi.py
sticker-0.0.5.dist-info/DESCRIPTION.rst
sticker-0.0.5.dist-info/METADATA
sticker-0.0.5.dist-info/RECORD
sticker-0.0.5.dist-info/WHEEL
sticker-0.0.5.dist-info/metadata.json
sticker-0.0.5.dist-info/top_level.txt
