Metadata-Version: 2.0
Name: sticker
Version: 0.0.5
Summary: Sticker is a powerful yet boilerplate-free alternative to writing your web API.
Home-page: https://github.com/rafaelcaricio/sticker
Author: Rafael Caricio
Author-email: sticker-dev@caric.io
License: Apache 2.0
Platform: UNKNOWN
Classifier: Development Status :: 2 - Pre-Alpha
Classifier: License :: OSI Approved :: Apache Software License
Classifier: Programming Language :: Python
Classifier: Programming Language :: Python :: 3
Classifier: Programming Language :: Python :: 3.6
Classifier: Programming Language :: Python :: 3.7
Classifier: Programming Language :: Python :: 3 :: Only
Classifier: Programming Language :: Python :: Implementation :: CPython
Classifier: Programming Language :: Python :: Implementation :: PyPy
Classifier: Framework :: Bottle
Classifier: Framework :: AsyncIO
Classifier: Framework :: Flask
Classifier: Topic :: Internet :: WWW/HTTP
Classifier: Topic :: Internet :: WWW/HTTP :: HTTP Servers
Classifier: Topic :: Internet :: WWW/HTTP :: WSGI
Classifier: Topic :: Internet :: WWW/HTTP :: WSGI :: Server
Classifier: Topic :: Software Development :: Libraries :: Python Modules
Requires-Python: >=3.6.0
Provides-Extra: bottle
Provides-Extra: flask
Provides-Extra: sanic
Provides-Extra: tornado
Requires-Dist: pyyaml
Provides-Extra: bottle
Requires-Dist: bottle (>=0.12.13); extra == 'bottle'
Provides-Extra: flask
Requires-Dist: flask (>=0.12.2); extra == 'flask'
Provides-Extra: sanic
Requires-Dist: sanic (>=0.7.0); extra == 'sanic'
Provides-Extra: tornado
Requires-Dist: tornado (>=5.0.1); extra == 'tornado'
